jamd/__init__.py
jamd/github-markdown-css.min.css
jamd/github_markdown_template.py
jamd/jamd_viewer.py
jamd/markdown_parser.py
jamd/shell.py
jamd_viewer-0.8.dist-info/LICENSE
jamd_viewer-0.8.dist-info/METADATA
jamd_viewer-0.8.dist-info/WHEEL
jamd_viewer-0.8.dist-info/entry_points.txt
jamd_viewer-0.8.dist-info/top_level.txt
jamd_viewer-0.8.dist-info/RECORD
