Metadata-Version: 2.1
Name: jamd-viewer
Version: 0.8
Summary: A multiplatform desktop markdown viewer powered by flask-desktop-ui.
Home-page: https://github.com/jamofer/jamd-viewer
Author: Javier Moragón
Author-email: jamofer@gmail.com
License: UNKNOWN
Platform: UNKNOWN
Classifier: Development Status :: 4 - Beta
Classifier: Intended Audience :: Developers
Classifier: License :: OSI Approved :: MIT License
Classifier: Operating System :: MacOS :: MacOS X
Classifier: Operating System :: Microsoft :: Windows
Classifier: Operating System :: POSIX :: Linux
Classifier: Programming Language :: Python :: 2.7
Classifier: Programming Language :: Python :: 3.5
Classifier: Programming Language :: Python :: 3.6
Classifier: Programming Language :: Python :: 3.7
Classifier: Topic :: Desktop Environment
Classifier: Topic :: Text Processing :: Markup :: Markdown
Classifier: Topic :: Software Development :: User Interfaces
Requires-Python: !=3.0.*,!=3.1.*,!=3.2.*,!=3.3.*,!=3.4.*,<3.8,>=2.7
Requires-Dist: flask-desktop-ui
Requires-Dist: markdown
Provides-Extra: testing
Requires-Dist: flake8 ; extra == 'testing'
Requires-Dist: pytest ; extra == 'testing'
Requires-Dist: mock ; extra == 'testing'
